pyxtractors/__init__.py
pyxtractors/extractor.py
pyxtractors/processor.py
pyxtractors-0.2.0.dist-info/METADATA
pyxtractors-0.2.0.dist-info/WHEEL
pyxtractors-0.2.0.dist-info/top_level.txt
pyxtractors-0.2.0.dist-info/RECORD
