Metadata-Version: 2.4
Name: pyxtractors
Version: 0.2.0
Summary: Tools to configure a mapping extraction policy
Author: Alexander Smirnov
Author-email: alexsm.w@yandex.ru
Dynamic: author
Dynamic: author-email
Dynamic: summary
